timesystem.py
integral_timesystem-1.0.dist-info/METADATA
integral_timesystem-1.0.dist-info/WHEEL
integral_timesystem-1.0.dist-info/top_level.txt
integral_timesystem-1.0.dist-info/RECORD
