Metadata-Version: 2.1
Name: integral-timesystem
Version: 1.0
Summary: UNKNOWN
Home-page: UNKNOWN
Author: UNKNOWN
Author-email: UNKNOWN
License: Creative Commons Attribution-Noncommercial-Share Alike license
Platform: UNKNOWN
Requires-Dist: flask
Requires-Dist: requests
Requires-Dist: pylru
